gwf_target_group/__init__.py
gwf_target_group-1.0.1.dist-info/LICENSE
gwf_target_group-1.0.1.dist-info/METADATA
gwf_target_group-1.0.1.dist-info/WHEEL
gwf_target_group-1.0.1.dist-info/top_level.txt
gwf_target_group-1.0.1.dist-info/RECORD
