Metadata-Version: 2.1
Name: gwf-target-group
Version: 1.0.1
Summary: A wrapper for gwf for easy generation of output file paths
Home-page: https://github.com/jbethune/gwf_target_group
Author: Jörn Bethune
License: UNKNOWN
Platform: UNKNOWN
Classifier: Programming Language :: Python :: 3
Classifier: License :: OSI Approved :: GNU General Public License v3 or later (GPLv3+)
Classifier: Operating System :: OS Independent
Requires-Python: >=3.6
Requires-Dist: gwf (>=1.6.0)
